[
  {
    "id": 1,
    "categoryID": 1,
    "type": "mcq",
    "question": "What is the capital of France?",
    "answers": [
      "Paris",
      "London"
    ],
    "correctAnswer": "Paris",
    "img": "https://media.gettyimages.com/id/1298383663/photo/aerial-view-of-paris-streets-and-eiffel-tower-at-sunset-france.jpg?s=170667a&w=gi&k=20&c=7U_RBiO6T6FSTLRZ5jXZ2FUR3vpTX8Zxq_3W8E8teaY="
  },
  {
    "id": 2,
    "categoryID": 2,
    "type": "mcq",
    "question": "What is the largest planet in our solar system?",
    "answers": [
      "Jupiter",
      "Mars",
      "Earth",
      "Saturn",
      "Neptune"
    ],
    "correctAnswer": "Jupiter",
    "img": "https://upload.wikimedia.org/wikipedia/commons/thumb/2/2b/Jupiter_and_its_shrunken_Great_Red_Spot.jpg/800px-Jupiter_and_its_shrunken_Great_Red_Spot.jpg"
  },
  {
    "id": 3,
    "type": "mcq",
    "categoryID": 2,
    "question": "Who painted the Mona Lisa?",
    "answers": [
      "Leonardo da Vinci",
      "Pablo Picasso",
      "Vincent van Gogh"
    ],
    "correctAnswer": "Leonardo da Vinci",
    "img": "https://upload.wikimedia.org/wikipedia/commons/thumb/6/6a/Mona_Lisa.jpg/800px-Mona_Lisa.jpg"
  }
]
